ServletRumenjiaochengCYuyanBianchengWang/README.md
ServletRumenjiaochengCYuyanBianchengWang/__init__.py
ServletRumenjiaochengCYuyanBianchengWang/__main__.py
ServletRumenjiaochengCYuyanBianchengWang/file.epub
ServletRumenjiaochengCYuyanBianchengWang/index.html
ServletRumenjiaochengCYuyanBianchengWang/css/__init__.py
ServletRumenjiaochengCYuyanBianchengWang/css/annotations.css
ServletRumenjiaochengCYuyanBianchengWang/css/main.css
ServletRumenjiaochengCYuyanBianchengWang/css/normalize.css
ServletRumenjiaochengCYuyanBianchengWang/css/popup.css
ServletRumenjiaochengCYuyanBianchengWang/font/__init__.py
ServletRumenjiaochengCYuyanBianchengWang/font/fontello.eot
ServletRumenjiaochengCYuyanBianchengWang/font/fontello.svg
ServletRumenjiaochengCYuyanBianchengWang/font/fontello.ttf
ServletRumenjiaochengCYuyanBianchengWang/font/fontello.woff
ServletRumenjiaochengCYuyanBianchengWang/img/__init__.py
ServletRumenjiaochengCYuyanBianchengWang/img/annotator-glyph-sprite.png
ServletRumenjiaochengCYuyanBianchengWang/img/annotator-icon-sprite.png
ServletRumenjiaochengCYuyanBianchengWang/img/apple-touch-icon.png
ServletRumenjiaochengCYuyanBianchengWang/img/cancelfullscreen.png
ServletRumenjiaochengCYuyanBianchengWang/img/close.png
ServletRumenjiaochengCYuyanBianchengWang/img/fullscreen.png
ServletRumenjiaochengCYuyanBianchengWang/img/loader.gif
ServletRumenjiaochengCYuyanBianchengWang/img/menu-icon.png
ServletRumenjiaochengCYuyanBianchengWang/img/save.png
ServletRumenjiaochengCYuyanBianchengWang/img/saved.png
ServletRumenjiaochengCYuyanBianchengWang/img/settings-s.png
ServletRumenjiaochengCYuyanBianchengWang/img/settings.png
ServletRumenjiaochengCYuyanBianchengWang/img/star.png
ServletRumenjiaochengCYuyanBianchengWang/js/__init__.py
ServletRumenjiaochengCYuyanBianchengWang/js/epub.js
ServletRumenjiaochengCYuyanBianchengWang/js/epub.min.js
ServletRumenjiaochengCYuyanBianchengWang/js/epub.min.map
ServletRumenjiaochengCYuyanBianchengWang/js/hooks.min.js
servlet_rumenjiaocheng_c_yuyan_biancheng_wang-2024.3.5.0.dist-info/METADATA
servlet_rumenjiaocheng_c_yuyan_biancheng_wang-2024.3.5.0.dist-info/WHEEL
servlet_rumenjiaocheng_c_yuyan_biancheng_wang-2024.3.5.0.dist-info/entry_points.txt
servlet_rumenjiaocheng_c_yuyan_biancheng_wang-2024.3.5.0.dist-info/top_level.txt
servlet_rumenjiaocheng_c_yuyan_biancheng_wang-2024.3.5.0.dist-info/RECORD
